go_cqhttpsdk/__init__.py
go_cqhttpsdk/client.py
go_cqhttpsdk/cq.py
go_cqhttpsdk/go_cqhttpsdk.py
go_cqhttpsdk/go_cqhttpserver.py
luoxis-1.0.dist-info/LICENSE
luoxis-1.0.dist-info/METADATA
luoxis-1.0.dist-info/WHEEL
luoxis-1.0.dist-info/top_level.txt
luoxis-1.0.dist-info/RECORD
